Workbook

Sheet README
B1: ISO/IEC 27090 AI Security Readiness Scanner
B2: Assess where your enterprise stands against ISO/IEC 27090 AI-security guidance and what remains to reach full alignment — sequenced into a 30-day plan.
B4: HOW TO USE
B5: 1. Scope | C5: List the AI systems in scope (built, fine-tuned, consumed, embedded vendor AI, RAG pipelines, agents). Assess at enterprise level, or copy the Scanner sheet per critical AI system.
B6: 2. Score | C6: On the Scanner sheet, pick a maturity score (0–4) or N/A in the yellow "Current maturity" column for each of the 54 controls. Record evidence in the notes column.
B7: 3. Read results | C7: Dashboard shows overall readiness, readiness by domain and priority, and open items per 30-day phase. Threat Coverage shows how well each of the 12 ISO/IEC 27090 threats (plus Annex B) is covered.
B8: 4. Act | C8: Filter the Scanner on Status = Gap / Partial and use the 30-Day Roadmap sheet to sequence remediation. P1 controls are the 30-day critical baseline.
B10: MATURITY SCALE
B11: 0 – Not in place | C11: No control exists.
B12: 1 – Ad hoc | C12: Informal, undocumented, person-dependent.
B13: 2 – Partial | C13: Defined for some AI systems or not consistently enforced.
B14: 3 – Implemented | C14: Defined, enforced across all in-scope AI systems, evidence exists.
B15: 4 – Managed | C15: Measured, monitored, continuously improved and audit-ready.
B17: SCORING LOGIC
B18: Target | C18: Full alignment target is 3 (Implemented) for every applicable control; raise to 4 for high-risk systems if desired.
B19: Readiness % | C19: Sum of min(score, target) ÷ sum of targets over applicable controls. Unassessed controls count as 0 (a gap until proven otherwise). N/A controls are excluded.
B20: Status | C20: Aligned = score ≥ target · Partial = 1 below target · Gap = 2+ below target · Not assessed = blank.
B21: Priority | C21: P1 = critical baseline, close within 30 days · P2 = close within 30 days where feasible · P3 = Day 31–90 backlog.
B23: IMPORTANT NOTES
B24: Not certifiable | C24: ISO/IEC 27090 is guidance, not a certifiable standard. "Compliance" here means alignment; certification runs through ISO/IEC 27001 (security) and ISO/IEC 42001 (AI management). Put the AI treatments into the 27001 risk treatment plan and SoA.
B25: Edition | C25: Controls are derived from practitioner analysis of ISO/IEC DIS 27090 (April 2025 draft). The first edition was reportedly published on 14 Oct 2026 — verify clause wording against the published edition before citing in audit evidence.
B26: Mappings | C26: ISO/IEC 27002, ISO/IEC 42001 and NIST SP 800-53 references are indicative practitioner mappings, not official concordances.
B27: Source | C27: Kompleye, "Securing AI Systems with ISO/IEC 27090", Oct 2026; ISO/IEC DIS 27090:2025 (paraphrased).

Sheet Scanner
A1: ISO/IEC 27090 AI Security Scanner — Self-Assessment
A2: Score each control in the yellow column. 0 Not in place · 1 Ad hoc · 2 Partial · 3 Implemented · 4 Managed · N/A not applicable.
A4: ID | B4: Domain | C4: Control | D4: Assessment question | E4: Threats addressed | F4: Priority | G4: 30-day phase | H4: Target | I4: Current maturity (0–4 / N/A) | J4: Gap | K4: Status | L4: Achieved | M4: Target (eff.) | N4: Evidence expected | O4: Evidence / notes | P4: Owner
A5: GOV-01 | B5: Governance & Scope | C5: AI system inventory | D5: Is there a complete, current inventory of all AI systems (incl. embedded vendor AI, RAG pipelines and agents) with owner, purpose and data used? | E5: ALL | F5: P1 | G5: Week 1 · Discover & Govern | H5: 3 | J5: =IF(OR(I5="",I5="N/A"),"",MAX(H5-I5,0)) | K5: =IF(I5="","Not assessed",IF(I5="N/A","N/A",IF(I5>=H5,"Aligned",IF(I5>=H5-1,"Partial","Gap")))) | L5: =IF(OR(I5="",I5="N/A"),0,MIN(I5,H5)) | M5: =IF(I5="N/A",0,H5) | N5: AI system inventory | P5: AI Governance Lead
A6: GOV-02 | B6: Governance & Scope | C6: AI asset register | D6: For each AI system, are training/test data, prep code, model code, hyperparameters, weights, inputs/outputs and retrieval stores recorded as assets with owners? | E6: ALL | F6: P1 | G6: Week 1 · Discover & Govern | H6: 3 | J6: =IF(OR(I6="",I6="N/A"),"",MAX(H6-I6,0)) | K6: =IF(I6="","Not assessed",IF(I6="N/A","N/A",IF(I6>=H6,"Aligned",IF(I6>=H6-1,"Partial","Gap")))) | L6: =IF(OR(I6="",I6="N/A"),0,MIN(I6,H6)) | M6: =IF(I6="N/A",0,H6) | N6: AI asset register per system | P6: System Owner
A7: GOV-03 | B7: Governance & Scope | C7: AI systems in ISMS scope | D7: Are AI systems and AI assets explicitly included in the ISO/IEC 27001 ISMS scope statement? | E7: ALL | F7: P1 | G7: Week 1 · Discover & Govern | H7: 3 | J7: =IF(OR(I7="",I7="N/A"),"",MAX(H7-I7,0)) | K7: =IF(I7="","Not assessed",IF(I7="N/A","N/A",IF(I7>=H7,"Aligned",IF(I7>=H7-1,"Partial","Gap")))) | L7: =IF(OR(I7="",I7="N/A"),0,MIN(I7,H7)) | M7: =IF(I7="N/A",0,H7) | N7: Updated ISMS scope | P7: ISMS Manager
A8: GOV-04 | B8: Governance & Scope | C8: AI governance programme | D8: Is there an AI governance programme with accountable owners, an AI policy and risk/impact assessment (aligned to ISO/IEC 42001)? | E8: ALL | F8: P2 | G8: Week 1 · Discover & Govern | H8: 3 | J8: =IF(OR(I8="",I8="N/A"),"",MAX(H8-I8,0)) | K8: =IF(I8="","Not assessed",IF(I8="N/A","N/A",IF(I8>=H8,"Aligned",IF(I8>=H8-1,"Partial","Gap")))) | L8: =IF(OR(I8="",I8="N/A"),0,MIN(I8,H8)) | M8: =IF(I8="N/A",0,H8) | N8: AI policy, RACI, governance charter | P8: CISO / CRO
A9: GOV-05 | B9: Governance & Scope | C9: AI-specific risk assessment | D9: Are the ISO/IEC 27090 AI threats included in the risk assessment and rated per AI system using the existing method? | E9: ALL | F9: P1 | G9: Week 1 · Discover & Govern | H9: 3 | J9: =IF(OR(I9="",I9="N/A"),"",MAX(H9-I9,0)) | K9: =IF(I9="","Not assessed",IF(I9="N/A","N/A",IF(I9>=H9,"Aligned",IF(I9>=H9-1,"Partial","Gap")))) | L9: =IF(OR(I9="",I9="N/A"),0,MIN(I9,H9)) | M9: =IF(I9="N/A",0,H9) | N9: AI risk assessments | P9: Risk Manager
A10: GOV-06 | B10: Governance & Scope | C10: SoA extended with AI treatments | D10: Does the Statement of Applicability include AI-specific risk treatments and map them to 27002 / 42001 controls? | E10: ALL | F10: P1 | G10: Week 4 · Validate & Evidence | H10: 3 | J10: =IF(OR(I10="",I10="N/A"),"",MAX(H10-I10,0)) | K10: =IF(I10="","Not assessed",IF(I10="N/A","N/A",IF(I10>=H10,"Aligned",IF(I10>=H10-1,"Partial","Gap")))) | L10: =IF(OR(I10="",I10="N/A"),0,MIN(I10,H10)) | M10: =IF(I10="N/A",0,H10) | N10: SoA with AI treatments | P10: ISMS Manager
A11: TMV-01 | B11: Threat Modelling & Validation | C11: Threat model all 12 AI threats | D11: Has every in-scope AI system been threat-modelled against all twelve ISO/IEC 27090 threats (not just prompt injection)? | E11: T01,T02,T03,T04,T05,T06,T07,T08,T09,T10,T11,T12,B01,B02,B03 | F11: P1 | G11: Week 1 · Discover & Govern | H11: 3 | J11: =IF(OR(I11="",I11="N/A"),"",MAX(H11-I11,0)) | K11: =IF(I11="","Not assessed",IF(I11="N/A","N/A",IF(I11>=H11,"Aligned",IF(I11>=H11-1,"Partial","Gap")))) | L11: =IF(OR(I11="",I11="N/A"),0,MIN(I11,H11)) | M11: =IF(I11="N/A",0,H11) | N11: Threat models per system | P11: Security Architect
A12: TMV-02 | B12: Threat Modelling & Validation | C12: AI red teaming before release | D12: Is AI red teaming (adversarial + harmful-output + classic vulns) performed before every major release? | E12: T02,T04,T05,T10,T11,T12 | F12: P1 | G12: Week 4 · Validate & Evidence | H12: 3 | J12: =IF(OR(I12="",I12="N/A"),"",MAX(H12-I12,0)) | K12: =IF(I12="","Not assessed",IF(I12="N/A","N/A",IF(I12>=H12,"Aligned",IF(I12>=H12-1,"Partial","Gap")))) | L12: =IF(OR(I12="",I12="N/A"),0,MIN(I12,H12)) | M12: =IF(I12="N/A",0,H12) | N12: Red-team reports | P12: Offensive Security
A13: TMV-03 | B13: Threat Modelling & Validation | C13: Joint mitigation portfolio testing | D13: When a new AI defence is added, is the full set of defences and model accuracy re-tested together? | E13: T01,T02,T03,T04,T05 | F13: P2 | G13: Week 4 · Validate & Evidence | H13: 3 | J13: =IF(OR(I13="",I13="N/A"),"",MAX(H13-I13,0)) | K13: =IF(I13="","Not assessed",IF(I13="N/A","N/A",IF(I13>=H13,"Aligned",IF(I13>=H13-1,"Partial","Gap")))) | L13: =IF(OR(I13="",I13="N/A"),0,MIN(I13,H13)) | M13: =IF(I13="N/A",0,H13) | N13: Regression & validation reports | P13: ML Engineering Lead
A14: TMV-04 | B14: Threat Modelling & Validation | C14: Continuous validation & drift testing | D14: Are models continuously validated against a held-out test set to detect drift or sudden behaviour changes? | E14: T01,T02,T06 | F14: P2 | G14: Week 4 · Validate & Evidence | H14: 3 | J14: =IF(OR(I14="",I14="N/A"),"",MAX(H14-I14,0)) | K14: =IF(I14="","Not assessed",IF(I14="N/A","N/A",IF(I14>=H14,"Aligned",IF(I14>=H14-1,"Partial","Gap")))) | L14: =IF(OR(I14="",I14="N/A"),0,MIN(I14,H14)) | M14: =IF(I14="N/A",0,H14) | N14: Validation schedule & results | P14: ML Engineering Lead
A15: TMV-05 | B15: Threat Modelling & Validation | C15: Defence decay management | D15: Is the effectiveness of AI defences monitored over time, with retraining and re-validation before redeployment? | E15: T01,T02,T03 | F15: P2 | G15: Day 31–90 · Backlog | H15: 3 | J15: =IF(OR(I15="",I15="N/A"),"",MAX(H15-I15,0)) | K15: =IF(I15="","Not assessed",IF(I15="N/A","N/A",IF(I15>=H15,"Aligned",IF(I15>=H15-1,"Partial","Gap")))) | L15: =IF(OR(I15="",I15="N/A"),0,MIN(I15,H15)) | M15: =IF(I15="N/A",0,H15) | N15: Defence effectiveness metrics | P15: ML Engineering Lead
A16: TMV-06 | B16: Threat Modelling & Validation | C16: Explainability & bias testing as attack signal | D16: Are explainability and bias tests run and reviewed as a potential signal of poisoning or manipulation? | E16: T01,T06,B03 | F16: P3 | G16: Day 31–90 · Backlog | H16: 3 | J16: =IF(OR(I16="",I16="N/A"),"",MAX(H16-I16,0)) | K16: =IF(I16="","Not assessed",IF(I16="N/A","N/A",IF(I16>=H16,"Aligned",IF(I16>=H16-1,"Partial","Gap")))) | L16: =IF(OR(I16="",I16="N/A"),0,MIN(I16,H16)) | M16: =IF(I16="N/A",0,H16) | N16: Bias / explainability reports | P16: Responsible AI Lead
... A58: OVS-02 | B58: Oversight & Transparency | C58: Transparency to users | D58: Are users informed when AI is involved and of its reliability and limitations? | E58: — | F58: P2 | G58: Week 4 · Validate & Evidence | H58: 3 | J58: =IF(OR(I58="",I58="N/A"),"",MAX(H58-I58,0)) | K58: =IF(I58="","Not assessed",IF(I58="N/A","N/A",IF(I58>=H58,"Aligned",IF(I58>=H58-1,"Partial","Gap")))) | L58: =IF(OR(I58="",I58="N/A"),0,MIN(I58,H58)) | M58: =IF(I58="N/A",0,H58) | N58: User-facing AI notices | P58: Product Owner

Sheet Dashboard
A1: ISO/IEC 27090 AI Security Readiness — Dashboard
A2: Live results from the Scanner sheet. Unassessed controls count as open gaps.
A4: Overall readiness | B4: Controls assessed | C4: Aligned | D4: Partial | E4: Gap | F4: Open P1 controls | G4: Verdict
A5: =IFERROR(SUM(Scanner!$L$5:$L$58)/SUM(Scanner!$M$5:$M$58),0) | B5: =COUNTA(Scanner!$I$5:$I$58)&" / 54" | C5: =COUNTIF(Scanner!$K$5:$K$58,"Aligned") | D5: =COUNTIF(Scanner!$K$5:$K$58,"Partial") | E5: =COUNTIF(Scanner!$K$5:$K$58,"Gap") | F5: =COUNTIFS(Scanner!$F$5:$F$58,"P1",Scanner!$K$5:$K$58,"<>Aligned",Scanner!$K$5:$K$58,"<>N/A") | G5: =IF(COUNTA(Scanner!$I$5:$I$58)=0,"Assessment not started",IF(AND(A5>=0.9,F5=0),"Aligned with 27090 baseline",IF(A5>=0.6,"Partially aligned","Significant gaps")))
A7: Readiness by domain
A8: Domain | B8: Controls | C8: Assessed | D8: Readiness % | E8: Aligned | F8: Partial | G8: Gap | H8: Open P1
A9: Governance & Scope | B9: =COUNTIF(Scanner!$B$5:$B$58,"Governance & Scope") | C9: =COUNTIFS(Scanner!$B$5:$B$58,"Governance & Scope",Scanner!$I$5:$I$58,"<>") | D9: =IFERROR(SUMIFS(Scanner!$L$5:$L$58,Scanner!$B$5:$B$58,"Governance & Scope")/SUMIFS(Scanner!$M$5:$M$58,Scanner!$B$5:$B$58,"Governance & Scope"),0) | E9: =COUNTIFS(Scanner!$B$5:$B$58,"Governance & Scope",Scanner!$K$5:$K$58,"Aligned") | F9: =COUNTIFS(Scanner!$B$5:$B$58,"Governance & Scope",Scanner!$K$5:$K$58,"Partial") | G9: =COUNTIFS(Scanner!$B$5:$B$58,"Governance & Scope",Scanner!$K$5:$K$58,"Gap") | H9: =COUNTIFS(Scanner!$B$5:$B$58,"Governance & Scope",Scanner!$F$5:$F$58,"P1",Scanner!$K$5:$K$58,"<>Aligned",Scanner!$K$5:$K$58,"<>N/A")
A10: Threat Modelling & Validation | B10: =COUNTIF(Scanner!$B$5:$B$58,"Threat Modelling & Validation") | C10: =COUNTIFS(Scanner!$B$5:$B$58,"Threat Modelling & Validation",Scanner!$I$5:$I$58,"<>") | D10: =IFERROR(SUMIFS(Scanner!$L$5:$L$58,Scanner!$B$5:$B$58,"Threat Modelling & Validation")/SUMIFS(Scanner!$M$5:$M$58,Scanner!$B$5:$B$58,"Threat Modelling & Validation"),0) | E10: =COUNTIFS(Scanner!$B$5:$B$58,"Threat Modelling & Validation",Scanner!$K$5:$K$58,"Aligned") | F10: =COUNTIFS(Scanner!$B$5:$B$58,"Threat Modelling & Validation",Scanner!$K$5:$K$58,"Partial") | G10: =COUNTIFS(Scanner!$B$5:$B$58,"Threat Modelling & Validation",Scanner!$K$5:$K$58,"Gap") | H10: =COUNTIFS(Scanner!$B$5:$B$58,"Threat Modelling & Validation",Scanner!$F$5:$F$58,"P1",Scanner!$K$5:$K$58,"<>Aligned",Scanner!$K$5:$K$58,"<>N/A")
A11: Secure AI Engineering | B11: =COUNTIF(Scanner!$B$5:$B$58,"Secure AI Engineering") | C11: =COUNTIFS(Scanner!$B$5:$B$58,"Secure AI Engineering",Scanner!$I$5:$I$58,"<>") | D11: =IFERROR(SUMIFS(Scanner!$L$5:$L$58,Scanner!$B$5:$B$58,"Secure AI Engineering")/SUMIFS(Scanner!$M$5:$M$58,Scanner!$B$5:$B$58,"Secure AI Engineering"),0) | E11: =COUNTIFS(Scanner!$B$5:$B$58,"Secure AI Engineering",Scanner!$K$5:$K$58,"Aligned") | F11: =COUNTIFS(Scanner!$B$5:$B$58,"Secure AI Engineering",Scanner!$K$5:$K$58,"Partial") | G11: =COUNTIFS(Scanner!$B$5:$B$58,"Secure AI Engineering",Scanner!$K$5:$K$58,"Gap") | H11: =COUNTIFS(Scanner!$B$5:$B$58,"Secure AI Engineering",Scanner!$F$5:$F$58,"P1",Scanner!$K$5:$K$58,"<>Aligned",Scanner!$K$5:$K$58,"<>N/A")
A12: AI Supply Chain | B12: =COUNTIF(Scanner!$B$5:$B$58,"AI Supply Chain") | C12: =COUNTIFS(Scanner!$B$5:$B$58,"AI Supply Chain",Scanner!$I$5:$I$58,"<>") | D12: =IFERROR(SUMIFS(Scanner!$L$5:$L$58,Scanner!$B$5:$B$58,"AI Supply Chain")/SUMIFS(Scanner!$M$5:$M$58,Scanner!$B$5:$B$58,"AI Supply Chain"),0) | E12: =COUNTIFS(Scanner!$B$5:$B$58,"AI Supply Chain",Scanner!$K$5:$K$58,"Aligned") | F12: =COUNTIFS(Scanner!$B$5:$B$58,"AI Supply Chain",Scanner!$K$5:$K$58,"Partial") | G12: =COUNTIFS(Scanner!$B$5:$B$58,"AI Supply Chain",Scanner!$K$5:$K$58,"Gap") | H12: =COUNTIFS(Scanner!$B$5:$B$58,"AI Supply Chain",Scanner!$F$5:$F$58,"P1",Scanner!$K$5:$K$58,"<>Aligned",Scanner!$K$5:$K$58,"<>N/A")
A13: Data Protection & Limitation | B13: =COUNTIF(Scanner!$B$5:$B$58,"Data Protection & Limitation") | C13: =COUNTIFS(Scanner!$B$5:$B$58,"Data Protection & Limitation",Scanner!$I$5:$I$58,"<>") | D13: =IFERROR(SUMIFS(Scanner!$L$5:$L$58,Scanner!$B$5:$B$58,"Data Protection & Limitation")/SUMIFS(Scanner!$M$5:$M$58,Scanner!$B$5:$B$58,"Data Protection & Limitation"),0) | E13: =COUNTIFS(Scanner!$B$5:$B$58,"Data Protection & Limitation",Scanner!$K$5:$K$58,"Aligned") | F13: =COUNTIFS(Scanner!$B$5:$B$58,"Data Protection & Limitation",Scanner!$K$5:$K$58,"Partial") | G13: =COUNTIFS(Scanner!$B$5:$B$58,"Data Protection & Limitation",Scanner!$K$5:$K$58,"Gap") | H13: =COUNTIFS(Scanner!$B$5:$B$58,"Data Protection & Limitation",Scanner!$F$5:$F$58,"P1",Scanner!$K$5:$K$58,"<>Aligned",Scanner!$K$5:$K$58,"<>N/A")
A14: Development Environment Protection | B14: =COUNTIF(Scanner!$B$5:$B$58,"Development Environment Protection") | C14: =COUNTIFS(Scanner!$B$5:$B$58,"Development Environment Protection",Scanner!$I$5:$I$58,"<>") | D14: =IFERROR(SUMIFS(Scanner!$L$5:$L$58,Scanner!$B$5:$B$58,"Development Environment Protection")/SUMIFS(Scanner!$M$5:$M$58,Scanner!$B$5:$B$58,"Development Environment Protection"),0) | E14: =COUNTIFS(Scanner!$B$5:$B$58,"Development Environment Protection",Scanner!$K$5:$K$58,"Aligned") | F14: =COUNTIFS(Scanner!$B$5:$B$58,"Development Environment Protection",Scanner!$K$5:$K$58,"Partial") | G14: =COUNTIFS(Scanner!$B$5:$B$58,"Development Environment Protection",Scanner!$K$5:$K$58,"Gap") | H14: =COUNTIFS(Scanner!$B$5:$B$58,"Development Environment Protection",Scanner!$F$5:$F$58,"P1",Scanner!$K$5:$K$58,"<>Aligned",Scanner!$K$5:$K$58,"<>N/A")
A15: Zero Trust & Access | B15: =COUNTIF(Scanner!$B$5:$B$58,"Zero Trust & Access") | C15: =COUNTIFS(Scanner!$B$5:$B$58,"Zero Trust & Access",Scanner!$I$5:$I$58,"<>") | D15: =IFERROR(SUMIFS(Scanner!$L$5:$L$58,Scanner!$B$5:$B$58,"Zero Trust & Access")/SUMIFS(Scanner!$M$5:$M$58,Scanner!$B$5:$B$58,"Zero Trust & Access"),0) | E15: =COUNTIFS(Scanner!$B$5:$B$58,"Zero Trust & Access",Scanner!$K$5:$K$58,"Aligned") | F15: =COUNTIFS(Scanner!$B$5:$B$58,"Zero Trust & Access",Scanner!$K$5:$K$58,"Partial") | G15: =COUNTIFS(Scanner!$B$5:$B$58,"Zero Trust & Access",Scanner!$K$5:$K$58,"Gap") | H15: =COUNTIFS(Scanner!$B$5:$B$58,"Zero Trust & Access",Scanner!$F$5:$F$58,"P1",Scanner!$K$5:$K$58,"<>Aligned",Scanner!$K$5:$K$58,"<>N/A")
A16: Runtime Defences | B16: =COUNTIF(Scanner!$B$5:$B$58,"Runtime Defences") | C16: =COUNTIFS(Scanner!$B$5:$B$58,"Runtime Defences",Scanner!$I$5:$I$58,"<>") | D16: =IFERROR(SUMIFS(Scanner!$L$5:$L$58,Scanner!$B$5:$B$58,"Runtime Defences")/SUMIFS(Scanner!$M$5:$M$58,Scanner!$B$5:$B$58,"Runtime Defences"),0) | E16: =COUNTIFS(Scanner!$B$5:$B$58,"Runtime Defences",Scanner!$K$5:$K$58,"Aligned") | F16: =COUNTIFS(Scanner!$B$5:$B$58,"Runtime Defences",Scanner!$K$5:$K$58,"Partial") | G16: =COUNTIFS(Scanner!$B$5:$B$58,"Runtime Defences",Scanner!$K$5:$K$58,"Gap") | H16: =COUNTIFS(Scanner!$B$5:$B$58,"Runtime Defences",Scanner!$F$5:$F$58,"P1",Scanner!$K$5:$K$58,"<>Aligned",Scanner!$K$5:$K$58,"<>N/A")
A17: Logging, Monitoring & Response | B17: =COUNTIF(Scanner!$B$5:$B$58,"Logging, Monitoring & Response") | C17: =COUNTIFS(Scanner!$B$5:$B$58,"Logging, Monitoring & Response",Scanner!$I$5:$I$58,"<>") | D17: =IFERROR(SUMIFS(Scanner!$L$5:$L$58,Scanner!$B$5:$B$58,"Logging, Monitoring & Response")/SUMIFS(Scanner!$M$5:$M$58,Scanner!$B$5:$B$58,"Logging, Monitoring & Response"),0) | E17: =COUNTIFS(Scanner!$B$5:$B$58,"Logging, Monitoring & Response",Scanner!$K$5:$K$58,"Aligned") | F17: =COUNTIFS(Scanner!$B$5:$B$58,"Logging, Monitoring & Response",Scanner!$K$5:$K$58,"Partial") | G17: =COUNTIFS(Scanner!$B$5:$B$58,"Logging, Monitoring & Response",Scanner!$K$5:$K$58,"Gap") | H17: =COUNTIFS(Scanner!$B$5:$B$58,"Logging, Monitoring & Response",Scanner!$F$5:$F$58,"P1",Scanner!$K$5:$K$58,"<>Aligned",Scanner!$K$5:$K$58,"<>N/A")
A18: Oversight & Transparency | B18: =COUNTIF(Scanner!$B$5:$B$58,"Oversight & Transparency") | C18: =COUNTIFS(Scanner!$B$5:$B$58,"Oversight & Transparency",Scanner!$I$5:$I$58,"<>") | D18: =IFERROR(SUMIFS(Scanner!$L$5:$L$58,Scanner!$B$5:$B$58,"Oversight & Transparency")/SUMIFS(Scanner!$M$5:$M$58,Scanner!$B$5:$B$58,"Oversight & Transparency"),0) | E18: =COUNTIFS(Scanner!$B$5:$B$58,"Oversight & Transparency",Scanner!$K$5:$K$58,"Aligned") | F18: =COUNTIFS(Scanner!$B$5:$B$58,"Oversight & Transparency",Scanner!$K$5:$K$58,"Partial") | G18: =COUNTIFS(Scanner!$B$5:$B$58,"Oversight & Transparency",Scanner!$K$5:$K$58,"Gap") | H18: =COUNTIFS(Scanner!$B$5:$B$58,"Oversight & Transparency",Scanner!$F$5:$F$58,"P1",Scanner!$K$5:$K$58,"<>Aligned",Scanner!$K$5:$K$58,"<>N/A")
A20: Readiness by priority
A21: Priority | B21: Controls | C21: Readiness % | D21: Open
A22: P1 - Critical baseline (within 30 days) | B22: =COUNTIF(Scanner!$F$5:$F$58,"P1") | C22: =IFERROR(SUMIFS(Scanner!$L$5:$L$58,Scanner!$F$5:$F$58,"P1")/SUMIFS(Scanner!$M$5:$M$58,Scanner!$F$5:$F$58,"P1"),0) | D22: =COUNTIFS(Scanner!$F$5:$F$58,"P1",Scanner!$K$5:$K$58,"<>Aligned",Scanner!$K$5:$K$58,"<>N/A")
A23: P2 - Important (within 30 days if feasible) | B23: =COUNTIF(Scanner!$F$5:$F$58,"P2") | C23: =IFERROR(SUMIFS(Scanner!$L$5:$L$58,Scanner!$F$5:$F$58,"P2")/SUMIFS(Scanner!$M$5:$M$58,Scanner!$F$5:$F$58,"P2"),0) | D23: =COUNTIFS(Scanner!$F$5:$F$58,"P2",Scanner!$K$5:$K$58,"<>Aligned",Scanner!$K$5:$K$58,"<>N/A")
A24: P3 - Day 31-90 backlog | B24: =COUNTIF(Scanner!$F$5:$F$58,"P3") | C24: =IFERROR(SUMIFS(Scanner!$L$5:$L$58,Scanner!$F$5:$F$58,"P3")/SUMIFS(Scanner!$M$5:$M$58,Scanner!$F$5:$F$58,"P3"),0) | D24: =COUNTIFS(Scanner!$F$5:$F$58,"P3",Scanner!$K$5:$K$58,"<>Aligned",Scanner!$K$5:$K$58,"<>N/A")
A26: Open items by 30-day phase
A27: 30-day phase | B27: Controls | C27: Open items | D27: Readiness %
A28: Week 1 · Discover & Govern | B28: =COUNTIF(Scanner!$G$5:$G$58,"Week 1 · Discover & Govern") | C28: =COUNTIFS(Scanner!$G$5:$G$58,"Week 1 · Discover & Govern",Scanner!$K$5:$K$58,"<>Aligned",Scanner!$K$5:$K$58,"<>N/A") | D28: =IFERROR(SUMIFS(Scanner!$L$5:$L$58,Scanner!$G$5:$G$58,"Week 1 · Discover & Govern")/SUMIFS(Scanner!$M$5:$M$58,Scanner!$G$5:$G$58,"Week 1 · Discover & Govern"),0)
A29: Week 2 · Harden Build-time | B29: =COUNTIF(Scanner!$G$5:$G$58,"Week 2 · Harden Build-time") | C29: =COUNTIFS(Scanner!$G$5:$G$58,"Week 2 · Harden Build-time",Scanner!$K$5:$K$58,"<>Aligned",Scanner!$K$5:$K$58,"<>N/A") | D29: =IFERROR(SUMIFS(Scanner!$L$5:$L$58,Scanner!$G$5:$G$58,"Week 2 · Harden Build-time")/SUMIFS(Scanner!$M$5:$M$58,Scanner!$G$5:$G$58,"Week 2 · Harden Build-time"),0)
A30: Week 3 · Secure Runtime | B30: =COUNTIF(Scanner!$G$5:$G$58,"Week 3 · Secure Runtime") | C30: =COUNTIFS(Scanner!$G$5:$G$58,"Week 3 · Secure Runtime",Scanner!$K$5:$K$58,"<>Aligned",Scanner!$K$5:$K$58,"<>N/A") | D30: =IFERROR(SUMIFS(Scanner!$L$5:$L$58,Scanner!$G$5:$G$58,"Week 3 · Secure Runtime")/SUMIFS(Scanner!$M$5:$M$58,Scanner!$G$5:$G$58,"Week 3 · Secure Runtime"),0)
A31: Week 4 · Validate & Evidence | B31: =COUNTIF(Scanner!$G$5:$G$58,"Week 4 · Validate & Evidence") | C31: =COUNTIFS(Scanner!$G$5:$G$58,"Week 4 · Validate & Evidence",Scanner!$K$5:$K$58,"<>Aligned",Scanner!$K$5:$K$58,"<>N/A") | D31: =IFERROR(SUMIFS(Scanner!$L$5:$L$58,Scanner!$G$5:$G$58,"Week 4 · Validate & Evidence")/SUMIFS(Scanner!$M$5:$M$58,Scanner!$G$5:$G$58,"Week 4 · Validate & Evidence"),0)
A32: Day 31–90 · Backlog | B32: =COUNTIF(Scanner!$G$5:$G$58,"Day 31–90 · Backlog") | C32: =COUNTIFS(Scanner!$G$5:$G$58,"Day 31–90 · Backlog",Scanner!$K$5:$K$58,"<>Aligned",Scanner!$K$5:$K$58,"<>N/A") | D32: =IFERROR(SUMIFS(Scanner!$L$5:$L$58,Scanner!$G$5:$G$58,"Day 31–90 · Backlog")/SUMIFS(Scanner!$M$5:$M$58,Scanner!$G$5:$G$58,"Day 31–90 · Backlog"),0)

Sheet Threat Coverage
A1: ISO/IEC 27090 threat coverage
A2: How well your scored controls cover each of the twelve AI-specific threats and the Annex B attacks.
A4: Code | B4: Threat | C4: Life-cycle stage | D4: Property hit | E4: Detection | F4: Key mitigations | G4: Controls | H4: Coverage % | I4: Mapped controls
A5: T01 | B5: Data poisoning | C5: Development; runtime if continuous learning | D5: Integrity | E5: Dataset hashing/integrity checks, anomaly detection, trigger inversion, activation clustering | F5: Data provenance, dataset access control, sanitisation, ensembles, robust training, fine-pruning | G5: =SUMPRODUCT(--ISNUMBER(SEARCH(A5,Scanner!$E$5:$E$58))) | H5: =IFERROR(SUMPRODUCT(ISNUMBER(SEARCH(A5,Scanner!$E$5:$E$58))*Scanner!$L$5:$L$58)/SUMPRODUCT(ISNUMBER(SEARCH(A5,Scanner!$E$5:$E$58))*Scanner!$M$5:$M$58),0) | I5: TMV-01, TMV-03, TMV-04, TMV-05, TMV-06, ENG-02, SUP-03, SUP-04, DAT-01, DAT-02, DAT-03, DEV-01, DEV-04, RUN-08, RUN-11
A6: T02 | B6: Evasion (adversarial examples) | C6: Runtime | D6: Integrity | E6: Parallel detector models, input/output distribution monitoring | F6: Adversarial training, randomised smoothing, input denoising, ensembles, usage monitoring | G6: =SUMPRODUCT(--ISNUMBER(SEARCH(A6,Scanner!$E$5:$E$58))) | H6: =IFERROR(SUMPRODUCT(ISNUMBER(SEARCH(A6,Scanner!$E$5:$E$58))*Scanner!$L$5:$L$58)/SUMPRODUCT(ISNUMBER(SEARCH(A6,Scanner!$E$5:$E$58))*Scanner!$M$5:$M$58),0) | I6: TMV-01, TMV-02, TMV-03, TMV-04, TMV-05, DAT-08, RUN-02, RUN-05, RUN-06, RUN-07, RUN-08, MON-02, OVS-01
A7: T03 | B7: Membership inference | C7: Runtime | D7: Confidentiality (privacy) | E7: Query-pattern analysis, access auditing | F7: Differential privacy, data minimisation, query limits, hiding confidence scores, dropout | G7: =SUMPRODUCT(--ISNUMBER(SEARCH(A7,Scanner!$E$5:$E$58))) | H7: =IFERROR(SUMPRODUCT(ISNUMBER(SEARCH(A7,Scanner!$E$5:$E$58))*Scanner!$L$5:$L$58)/SUMPRODUCT(ISNUMBER(SEARCH(A7,Scanner!$E$5:$E$58))*Scanner!$M$5:$M$58),0) | I7: TMV-01, TMV-03, TMV-05, DAT-04, DAT-06, ZTA-02, RUN-04, RUN-05, RUN-06, MON-02
A8: T04 | B8: Model exfiltration | C8: Runtime | D8: Confidentiality (IP) | E8: Per-caller behaviour analytics, unusual query distributions | F8: Throttling, minimal outputs, access control, watermarking | G8: =SUMPRODUCT(--ISNUMBER(SEARCH(A8,Scanner!$E$5:$E$58))) | H8: =IFERROR(SUMPRODUCT(ISNUMBER(SEARCH(A8,Scanner!$E$5:$E$58))*Scanner!$L$5:$L$58)/SUMPRODUCT(ISNUMBER(SEARCH(A8,Scanner!$E$5:$E$58))*Scanner!$M$5:$M$58),0) | I8: TMV-01, TMV-02, TMV-03, DAT-08, ZTA-02, RUN-05, RUN-06, RUN-07, RUN-10, MON-02
A9: T05 | B9: Model inversion | C9: Runtime | D9: Confidentiality | E9: As exfiltration; queries sweeping the input space | F9: Rate limits, differential privacy, obscured confidence | G9: =SUMPRODUCT(--ISNUMBER(SEARCH(A9,Scanner!$E$5:$E$58))) | H9: =IFERROR(SUMPRODUCT(ISNUMBER(SEARCH(A9,Scanner!$E$5:$E$58))*Scanner!$L$5:$L$58)/SUMPRODUCT(ISNUMBER(SEARCH(A9,Scanner!$E$5:$E$58))*Scanner!$M$5:$M$58),0) | I9: TMV-01, TMV-02, TMV-03, DAT-04, DAT-06, DAT-08, ZTA-02, RUN-04, RUN-05, RUN-06, RUN-07, MON-02
A10: T06 | B10: Direct model poisoning | C10: Development, supply chain, runtime | D10: Integrity | E10: General attack detection, threat intel on model sources | F10: Protect dev/runtime environments, trusted execution, supply-chain controls | G10: =SUMPRODUCT(--ISNUMBER(SEARCH(A10,Scanner!$E$5:$E$58))) | H10: =IFERROR(SUMPRODUCT(ISNUMBER(SEARCH(A10,Scanner!$E$5:$E$58))*Scanner!$L$5:$L$58)/SUMPRODUCT(ISNUMBER(SEARCH(A10,Scanner!$E$5:$E$58))*Scanner!$M$5:$M$58),0) | I10: TMV-01, TMV-04, TMV-06, ENG-01, ENG-02, ENG-03, ENG-04, SUP-01, SUP-02, SUP-03, SUP-04, SUP-05, DEV-01, DEV-02, DEV-04
A11: T07 | B11: Direct model theft | C11: Development, runtime | D11: Confidentiality (IP) | E11: General attack detection | F11: Environment hardening, trusted execution, model obfuscation | G11: =SUMPRODUCT(--ISNUMBER(SEARCH(A11,Scanner!$E$5:$E$58))) | H11: =IFERROR(SUMPRODUCT(ISNUMBER(SEARCH(A11,Scanner!$E$5:$E$58))*Scanner!$L$5:$L$58)/SUMPRODUCT(ISNUMBER(SEARCH(A11,Scanner!$E$5:$E$58))*Scanner!$M$5:$M$58),0) | I11: TMV-01, ENG-01, ENG-03, SUP-05, DEV-01, DEV-02, DEV-03, DEV-04, RUN-10
A12: T08 | B12: Training data leak | C12: Development; runtime if data collected live | D12: Confidentiality | E12: Data loss detection | F12: Standard data protection, least privilege, federated learning | G12: =SUMPRODUCT(--ISNUMBER(SEARCH(A12,Scanner!$E$5:$E$58))) | H12: =IFERROR(SUMPRODUCT(ISNUMBER(SEARCH(A12,Scanner!$E$5:$E$58))*Scanner!$L$5:$L$58)/SUMPRODUCT(ISNUMBER(SEARCH(A12,Scanner!$E$5:$E$58))*Scanner!$M$5:$M$58),0) | I12: TMV-01, SUP-04, SUP-05, DAT-01, DAT-04, DAT-05, DEV-01, DEV-04, MON-03
A13: T09 | B13: Model input leak | C13: Runtime | D13: Confidentiality | E13: Data loss detection | F13: Encryption, access control, align RAG content with user rights | G13: =SUMPRODUCT(--ISNUMBER(SEARCH(A13,Scanner!$E$5:$E$58))) | H13: =IFERROR(SUMPRODUCT(ISNUMBER(SEARCH(A13,Scanner!$E$5:$E$58))*Scanner!$L$5:$L$58)/SUMPRODUCT(ISNUMBER(SEARCH(A13,Scanner!$E$5:$E$58))*Scanner!$M$5:$M$58),0) | I13: TMV-01, DAT-05, DAT-07, ZTA-03, MON-03
A14: T10 | B14: Sensitive model output | C14: Runtime | D14: Confidentiality | E14: Pattern-based output scanning | F14: Output filtering and redaction | G14: =SUMPRODUCT(--ISNUMBER(SEARCH(A14,Scanner!$E$5:$E$58))) | H14: =IFERROR(SUMPRODUCT(ISNUMBER(SEARCH(A14,Scanner!$E$5:$E$58))*Scanner!$L$5:$L$58)/SUMPRODUCT(ISNUMBER(SEARCH(A14,Scanner!$E$5:$E$58))*Scanner!$M$5:$M$58),0) | I14: TMV-01, TMV-02, DAT-04, DAT-06, DAT-07, RUN-02, RUN-04, MON-03
A15: T11 | B15: Prompt injection | C15: Runtime | D15: Integrity, confidentiality | E15: Input/output classifiers, logging heuristics | F15: Input segregation, least model privilege, limit untrusted sources, hardened system prompts | G15: =SUMPRODUCT(--ISNUMBER(SEARCH(A15,Scanner!$E$5:$E$58))) | H15: =IFERROR(SUMPRODUCT(ISNUMBER(SEARCH(A15,Scanner!$E$5:$E$58))*Scanner!$L$5:$L$58)/SUMPRODUCT(ISNUMBER(SEARCH(A15,Scanner!$E$5:$E$58))*Scanner!$M$5:$M$58),0) | I15: TMV-01, TMV-02, DAT-07, ZTA-02, ZTA-04, RUN-01, RUN-02, MON-02, OVS-01
A16: T12 | B16: Output injection | C16: Runtime | D16: Integrity | E16: Standard output validation | F16: Treat output as untrusted; encode and validate before use | G16: =SUMPRODUCT(--ISNUMBER(SEARCH(A16,Scanner!$E$5:$E$58))) | H16: =IFERROR(SUMPRODUCT(ISNUMBER(SEARCH(A16,Scanner!$E$5:$E$58))*Scanner!$L$5:$L$58)/SUMPRODUCT(ISNUMBER(SEARCH(A16,Scanner!$E$5:$E$58))*Scanner!$M$5:$M$58),0) | I16: TMV-01, TMV-02, ZTA-04, RUN-03, OVS-01
... A19: B03 | B19: Architectural backdoors (Annex B) | C19: Development, supply chain | D19: Integrity | E19: Model review, threat intel on model sources | F19: Vetted model sources, provenance, change control | G19: =SUMPRODUCT(--ISNUMBER(SEARCH(A19,Scanner!$E$5:$E$58))) | H19: =IFERROR(SUMPRODUCT(ISNUMBER(SEARCH(A19,Scanner!$E$5:$E$58))*Scanner!$L$5:$L$58)/SUMPRODUCT(ISNUMBER(SEARCH(A19,Scanner!$E$5:$E$58))*Scanner!$M$5:$M$58),0) | I19: TMV-01, TMV-06, ENG-01, ENG-04, SUP-01, SUP-03

Sheet 30-Day Roadmap
A1: 30-Day Plan to Secure Enterprise AI Systems (ISO/IEC 27090)
A2: Week-by-week sequence. Open items update live from the Scanner. P1 controls are the critical baseline to close within 30 days; P3 items roll into the Day 31–90 backlog.
A4: Phase | B4: Days | C4: Objective | D4: Key actions | E4: Controls | F4: Exit criteria / evidence | G4: Lead | H4: Open items
A5: Week 1 · Discover & Govern | B5: Days 1–7 | C5: Know what you have and bring it under governance | D5: • Stand up an AI security tiger team with a RACI • Complete the AI system inventory, including shadow and vendor-embedded AI, RAG and agents • Build asset registers for the critical AI systems • Bring AI into the ISO 27001 ISMS scope and risk register • Threat-model the top critical systems against all 12 ISO/IEC 27090 threats • Turn on baseline AI interaction logging | E5: GOV-01, GOV-02, GOV-03, GOV-04, GOV-05, TMV-01, MON-01 | F5: AI inventory, asset registers, updated ISMS scope, AI risk entries, threat models for critical systems, log schema live | G5: CISO + AI Governance Lead | H5: =COUNTIFS(Scanner!$G$5:$G$58,"Week 1 · Discover & Govern",Scanner!$K$5:$K$58,"<>Aligned",Scanner!$K$5:$K$58,"<>N/A")
A6: Week 2 · Harden Build-time | B6: Days 8–14 | C6: Protect where the crown jewels live: the build environment | D6: • Segregate and encrypt the data-science / MLOps environment • Enforce JIT privileged access to weights, datasets and pipelines • Produce an AIBOM per critical system; verify signatures and pin dependencies • Hash datasets and record lineage • Vet third-party pretrained models and ML tooling • Apply the secure SDLC to data-science code | E6: ENG-01, ENG-02, ENG-03, ENG-04, SUP-01, SUP-02, SUP-03, SUP-05, DAT-01, DAT-02, DAT-03, DAT-04, DEV-01, DEV-02, DEV-03, DEV-04 | F6: Environment architecture evidence, PAM/access reviews, AIBOMs, integrity logs, approved model & tooling list | G6: Cloud Platform + Data Engineering | H6: =COUNTIFS(Scanner!$G$5:$G$58,"Week 2 · Harden Build-time",Scanner!$K$5:$K$58,"<>Aligned",Scanner!$K$5:$K$58,"<>N/A")
A7: Week 3 · Secure Runtime | B7: Days 15–21 | C7: Make the running model hard to abuse | D7: • Authenticate and authorise every model endpoint • Apply least model privilege to agents and plug-ins • Deploy prompt-injection design patterns and input/output guardrails • Validate and encode all model output; redact sensitive output • Enforce per-user rate limits, token caps and cost quotas • Enforce entitlement-aware RAG retrieval • Ship SOC detections for AI attack patterns | E7: DAT-07, ZTA-01, ZTA-02, ZTA-03, ZTA-04, RUN-01, RUN-02, RUN-03, RUN-04, RUN-05, RUN-06, RUN-07, RUN-09, MON-02, MON-03, OVS-01 | F7: Endpoint access policy, agent entitlement register, guardrail configs and tests, rate-limit policy, SIEM AI rule catalogue | G7: Application Owners + SOC | H7: =COUNTIFS(Scanner!$G$5:$G$58,"Week 3 · Secure Runtime",Scanner!$K$5:$K$58,"<>Aligned",Scanner!$K$5:$K$58,"<>N/A")
A8: Week 4 · Validate & Evidence | B8: Days 22–30 | C8: Prove it works and produce audit-ready evidence | D8: • Red-team the critical AI systems • Regression-test the defence portfolio together with model accuracy • Set the continuous validation and drift schedule • Publish AI incident playbooks and run a tabletop • Extend the SoA with AI treatments • Request supplier assurances covering data and models • Publish user transparency notices • Re-run this scanner and brief leadership | E8: GOV-06, TMV-02, TMV-03, TMV-04, SUP-04, MON-04, OVS-02 | F8: Red-team and validation reports, IR playbooks plus exercise record, extended SoA, supplier assurances, re-scan results | G8: CISO + Offensive Security | H8: =COUNTIFS(Scanner!$G$5:$G$58,"Week 4 · Validate & Evidence",Scanner!$K$5:$K$58,"<>Aligned",Scanner!$K$5:$K$58,"<>N/A")
A9: Day 31–90 · Backlog | B9: Days 31–90 | C9: Close the long tail and extend to all AI systems | D9: • Privacy-enhancing techniques • Retention and deletion of AI data • Robustness hardening for high-risk models • Watermarking for proprietary models • Continuous-learning safeguards • Defence decay management • Explainability and bias testing • Limit public model disclosures • Roll out controls to the remaining AI systems | E9: TMV-05, TMV-06, DAT-05, DAT-06, DAT-08, RUN-08, RUN-10, RUN-11 | F9: Backlog closure evidence; readiness for ISO 27001 / 42001 audit | G9: AI Governance Lead | H9: =COUNTIFS(Scanner!$G$5:$G$58,"Day 31–90 · Backlog",Scanner!$K$5:$K$58,"<>Aligned",Scanner!$K$5:$K$58,"<>N/A")
A11: Governance cadence
A12: Daily | B12: 15-minute tiger-team stand-up on blockers
A13: Weekly | B13: Steering review with CISO / CIO: re-score changed controls and review the Dashboard
A14: Day 30 | B14: Leadership readout: readiness %, open P1s, residual risk acceptance, Day 31–90 plan

Sheet Control Catalogue
A1: ISO/IEC 27090 AI Security Control Catalogue (54 controls)
A2: Controls derived from ISO/IEC DIS 27090 threats, foundational practices and cross-cutting mitigations. Framework references are indicative practitioner mappings.
A4: ID | B4: Domain | C4: Control | D4: Requirement (what good looks like) | E4: ISO/IEC 27090 threats | F4: ISO/IEC 27002:2022 | G4: ISO/IEC 42001 | H4: NIST SP 800-53 / other | I4: Audit evidence | J4: Priority | K4: 30-day phase | L4: Owner
A5: GOV-01 | B5: Governance & Scope | C5: AI system inventory | D5: Complete inventory of every AI system built, fine-tuned or consumed — including vendor-embedded AI, copilots, RAG pipelines and agents — with owner, purpose and data used. | E5: ALL | F5: 5.9 | G5: AIMS scope | H5: PM-5, CM-8 | I5: AI system inventory | J5: P1 | K5: Week 1 · Discover & Govern | L5: AI Governance Lead
A6: GOV-02 | B6: Governance & Scope | C6: AI asset register | D6: For each AI system, record its AI assets: training/test data, data-prep code, model code & hyperparameters, trained weights, inference inputs/outputs and retrieval stores. | E6: ALL | F6: 5.9 | G6: — | H6: CM-8 | I6: AI asset register per system | J6: P1 | K6: Week 1 · Discover & Govern | L6: System Owner
A7: GOV-03 | B7: Governance & Scope | C7: AI systems in ISMS scope | D7: AI systems and their assets are formally within the ISO/IEC 27001 ISMS scope and subject to its risk process. | E7: ALL | F7: 27001 cl. 4.3 | G7: — | H7: PM-9 | I7: Updated ISMS scope | J7: P1 | K7: Week 1 · Discover & Govern | L7: ISMS Manager
A8: GOV-04 | B8: Governance & Scope | C8: AI governance programme | D8: An AI governance programme (AI management system per ISO/IEC 42001) with accountable roles, AI policy, and risk & impact assessment. | E8: ALL | F8: 5.1, 5.2 | G8: AIMS (42001) | H8: PM-9, RA-3 | I8: AI policy, RACI, governance charter | J8: P2 | K8: Week 1 · Discover & Govern | L8: CISO / CRO
A9: GOV-05 | B9: Governance & Scope | C9: AI-specific risk assessment | D9: The 27090 threats are added to the existing risk method; likelihood and impact rated per AI system and stage. | E9: ALL | F9: 27001 cl. 6.1.2 | G9: — | H9: RA-3 | I9: AI risk assessments | J9: P1 | K9: Week 1 · Discover & Govern | L9: Risk Manager
A10: GOV-06 | B10: Governance & Scope | C10: SoA extended with AI treatments | D10: Statement of Applicability maps AI treatments to 27002 controls and adds AI-specific measures (provenance, throttling, confidence obscuring, guardrails) where no control fits. | E10: ALL | F10: 27001 SoA | G10: Annex A/B | H10: PM-9 | I10: SoA with AI treatments | J10: P1 | K10: Week 4 · Validate & Evidence | L10: ISMS Manager
A11: TMV-01 | B11: Threat Modelling & Validation | C11: Threat model all 12 AI threats | D11: Each AI system is threat-modelled against all twelve 27090 threats (plus Annex B) across its life-cycle stages and assets. | E11: T01,T02,T03,T04,T05,T06,T07,T08,T09,T10,T11,T12,B01,B02,B03 | F11: 8.25 | G11: A.6.2.3 | H11: RA-3, SA-8, SA-11(2) | I11: Threat models per system | J11: P1 | K11: Week 1 · Discover & Govern | L11: Security Architect
A12: TMV-02 | B12: Threat Modelling & Validation | C12: AI red teaming before release | D12: AI-informed red teaming covering adversarial attacks and harmful outputs, as well as classic vulnerabilities, before each major release. | E12: T02,T04,T05,T10,T11,T12 | F12: 8.29 | G12: A.6.2.6 | H12: CA-8, SA-11 | I12: Red-team reports | J12: P1 | K12: Week 4 · Validate & Evidence | L12: Offensive Security
A13: TMV-03 | B13: Threat Modelling & Validation | C13: Joint mitigation portfolio testing | D13: Whenever a mitigation is added, the whole defence portfolio and model accuracy are tested together, because defences can weaken each other. | E13: T01,T02,T03,T04,T05 | F13: 8.29 | G13: A.6.2.6 | H13: SA-11 | I13: Regression & validation reports | J13: P2 | K13: Week 4 · Validate & Evidence | L13: ML Engineering Lead
A14: TMV-04 | B14: Threat Modelling & Validation | C14: Continuous validation & drift testing | D14: Models are re-tested against a held-out set on a schedule to catch sudden behaviour change and drift. | E14: T01,T02,T06 | F14: 8.16 | G14: B.6.2.6 | H14: CA-7, RA-5 | I14: Validation schedule & results | J14: P2 | K14: Week 4 · Validate & Evidence | L14: ML Engineering Lead
A15: TMV-05 | B15: Threat Modelling & Validation | C15: Defence decay management | D15: Effectiveness of training-based defences is monitored in operation; models retrained when needed and re-validated before redeployment. | E15: T01,T02,T03 | F15: 8.29 | G15: B.6.2.6 | H15: CA-7 | I15: Defence effectiveness metrics | J15: P2 | K15: Day 31–90 · Backlog | L15: ML Engineering Lead
... A58: OVS-02 | B58: Oversight & Transparency | C58: Transparency to users | D58: Users are told when AI is involved and how reliable it is, to curb over-reliance. | E58: — | F58: — | G58: B.7.2 | H58: — | I58: User-facing AI notices | J58: P2 | K58: Week 4 · Validate & Evidence | L58: Product Owner
A60: Threat codes | B60: T01 Data poisoning · T02 Evasion · T03 Membership inference · T04 Model exfiltration · T05 Model inversion · T06 Direct model poisoning · T07 Direct model theft · T08 Training data leak · T09 Model input leak · T10 Sensitive model output · T11 Prompt injection · T12 Output injection · B01–B03 Annex B (resource exhaustion, compromised libraries/RNG, architectural backdoors)
